[
  {
    "timestamp": "2025-06-17T14:03:23.787745+00:00",
    "topico": "alarme/evento",
    "valor": "\ud83d\udd12 Alarme ativado."
  },
  {
    "timestamp": "2025-06-17T14:03:31.658280+00:00",
    "topico": "alarme/evento",
    "valor": "\ud83d\udea8 Alarme disparado! Porta TRIAGEM foi aberta."
  },
  {
    "timestamp": "2025-06-17T14:03:32.279184+00:00",
    "topico": "alarme/evento",
    "valor": "\ud83d\udea8 Alarme disparado! Porta TRIAGEM foi aberta."
  },
  {
    "timestamp": "2025-06-17T14:03:32.794138+00:00",
    "topico": "alarme/evento",
    "valor": "\ud83d\udea8 Alarme disparado! Porta TRIAGEM foi aberta."
  },
  {
    "timestamp": "2025-06-17T14:03:33.279413+00:00",
    "topico": "alarme/evento",
    "valor": "\ud83d\udea8 Alarme disparado! Porta TRIAGEM foi aberta."
  },
  {
    "timestamp": "2025-06-17T14:03:33.844433+00:00",
    "topico": "alarme/evento",
    "valor": "\ud83d\udea8 Alarme disparado! Porta TRIAGEM foi aberta."
  },
  {
    "timestamp": "2025-06-17T14:03:34.324619+00:00",
    "topico": "alarme/evento",
    "valor": "\ud83d\udea8 Alarme disparado! Porta TRIAGEM foi aberta."
  },
  {
    "timestamp": "2025-06-17T14:03:34.863174+00:00",
    "topico": "alarme/evento",
    "valor": "\ud83d\udea8 Alarme disparado! Porta TRIAGEM foi aberta."
  },
  {
    "timestamp": "2025-06-17T14:03:35.429167+00:00",
    "topico": "alarme/evento",
    "valor": "\ud83d\udea8 Alarme disparado! Porta TRIAGEM foi aberta."
  },
  {
    "timestamp": "2025-06-17T14:03:35.933501+00:00",
    "topico": "alarme/evento",
    "valor": "\ud83d\udea8 Alarme disparado! Porta TRIAGEM foi aberta."
  },
  {
    "timestamp": "2025-06-17T14:03:36.454426+00:00",
    "topico": "alarme/evento",
    "valor": "\ud83d\udea8 Alarme disparado! Porta TRIAGEM foi aberta."
  },
  {
    "timestamp": "2025-06-17T14:03:36.989715+00:00",
    "topico": "alarme/evento",
    "valor": "\ud83d\udea8 Alarme disparado! Porta TRIAGEM foi aberta."
  },
  {
    "timestamp": "2025-06-17T14:03:37.527386+00:00",
    "topico": "alarme/evento",
    "valor": "\ud83d\udea8 Alarme disparado! Porta TRIAGEM foi aberta."
  },
  {
    "timestamp": "2025-06-17T14:03:38.059511+00:00",
    "topico": "alarme/evento",
    "valor": "\ud83d\udea8 Alarme disparado! Porta TRIAGEM foi aberta."
  },
  {
    "timestamp": "2025-06-17T14:03:38.581536+00:00",
    "topico": "alarme/evento",
    "valor": "\ud83d\udea8 Alarme disparado! Porta TRIAGEM foi aberta."
  },
  {
    "timestamp": "2025-06-17T14:03:39.154027+00:00",
    "topico": "alarme/evento",
    "valor": "\ud83d\udea8 Alarme disparado! Porta TRIAGEM foi aberta."
  },
  {
    "timestamp": "2025-06-17T14:03:39.643076+00:00",
    "topico": "alarme/evento",
    "valor": "\ud83d\udea8 Alarme disparado! Porta TRIAGEM foi aberta."
  },
  {
    "timestamp": "2025-06-17T14:03:40.192890+00:00",
    "topico": "alarme/evento",
    "valor": "\ud83d\udea8 Alarme disparado! Porta TRIAGEM foi aberta."
  },
  {
    "timestamp": "2025-06-17T14:03:40.648866+00:00",
    "topico": "alarme/evento",
    "valor": "\ud83d\udea8 Alarme disparado! Porta TRIAGEM foi aberta."
  },
  {
    "timestamp": "2025-06-17T14:03:41.114843+00:00",
    "topico": "alarme/evento",
    "valor": "\ud83d\udea8 Alarme disparado! Porta TRIAGEM foi aberta."
  },
  {
    "timestamp": "2025-06-17T14:03:41.650002+00:00",
    "topico": "alarme/evento",
    "valor": "\ud83d\udea8 Alarme disparado! Porta TRIAGEM foi aberta."
  },
  {
    "timestamp": "2025-06-17T14:03:42.173027+00:00",
    "topico": "alarme/evento",
    "valor": "\ud83d\udea8 Alarme disparado! Porta TRIAGEM foi aberta."
  },
  {
    "timestamp": "2025-06-17T14:03:42.834365+00:00",
    "topico": "alarme/evento",
    "valor": "\ud83d\udea8 Alarme disparado! Porta TRIAGEM foi aberta."
  },
  {
    "timestamp": "2025-06-17T14:03:43.261703+00:00",
    "topico": "alarme/evento",
    "valor": "\ud83d\udea8 Alarme disparado! Porta TRIAGEM foi aberta."
  },
  {
    "timestamp": "2025-06-17T14:03:43.768669+00:00",
    "topico": "alarme/evento",
    "valor": "\ud83d\udea8 Alarme disparado! Porta TRIAGEM foi aberta."
  },
  {
    "timestamp": "2025-06-17T14:03:44.224346+00:00",
    "topico": "alarme/evento",
    "valor": "\ud83d\udea8 Alarme disparado! Porta TRIAGEM foi aberta."
  },
  {
    "timestamp": "2025-06-17T14:03:44.750869+00:00",
    "topico": "alarme/evento",
    "valor": "\ud83d\udea8 Alarme disparado! Porta TRIAGEM foi aberta."
  },
  {
    "timestamp": "2025-06-17T14:03:45.334186+00:00",
    "topico": "alarme/evento",
    "valor": "\ud83d\udea8 Alarme disparado! Porta TRIAGEM foi aberta."
  },
  {
    "timestamp": "2025-06-17T14:03:45.862903+00:00",
    "topico": "alarme/evento",
    "valor": "\ud83d\udea8 Alarme disparado! Porta TRIAGEM foi aberta."
  },
  {
    "timestamp": "2025-06-17T14:03:46.356015+00:00",
    "topico": "alarme/evento",
    "valor": "\ud83d\udea8 Alarme disparado! Porta TRIAGEM foi aberta."
  },
  {
    "timestamp": "2025-06-17T14:03:46.810759+00:00",
    "topico": "alarme/evento",
    "valor": "\ud83d\udea8 Alarme disparado! Porta TRIAGEM foi aberta."
  },
  {
    "timestamp": "2025-06-17T14:03:47.269145+00:00",
    "topico": "alarme/evento",
    "valor": "\ud83d\udea8 Alarme disparado! Porta TRIAGEM foi aberta."
  },
  {
    "timestamp": "2025-06-17T14:03:47.781222+00:00",
    "topico": "alarme/evento",
    "valor": "\ud83d\udea8 Alarme disparado! Porta TRIAGEM foi aberta."
  },
  {
    "timestamp": "2025-06-17T14:03:48.322610+00:00",
    "topico": "alarme/evento",
    "valor": "\ud83d\udea8 Alarme disparado! Porta TRIAGEM foi aberta."
  },
  {
    "timestamp": "2025-06-17T14:03:48.830185+00:00",
    "topico": "alarme/evento",
    "valor": "\ud83d\udea8 Alarme disparado! Porta TRIAGEM foi aberta."
  },
  {
    "timestamp": "2025-06-17T14:03:49.364817+00:00",
    "topico": "alarme/evento",
    "valor": "\ud83d\udea8 Alarme disparado! Porta RECICLO foi aberta."
  },
  {
    "timestamp": "2025-06-17T14:03:49.774010+00:00",
    "topico": "alarme/evento",
    "valor": "\ud83d\udea8 Alarme disparado! Porta RECICLO foi aberta."
  },
  {
    "timestamp": "2025-06-17T14:03:50.284634+00:00",
    "topico": "alarme/evento",
    "valor": "\ud83d\udea8 Alarme disparado! Porta RECICLO foi aberta."
  },
  {
    "timestamp": "2025-06-17T14:03:50.834970+00:00",
    "topico": "alarme/evento",
    "valor": "\ud83d\udea8 Alarme disparado! Porta RECICLO foi aberta."
  },
  {
    "timestamp": "2025-06-17T14:03:51.364662+00:00",
    "topico": "alarme/evento",
    "valor": "\ud83d\udea8 Alarme disparado! Porta RECICLO foi aberta."
  },
  {
    "timestamp": "2025-06-17T14:03:51.970537+00:00",
    "topico": "alarme/evento",
    "valor": "\ud83d\udea8 Alarme disparado! Porta RECICLO foi aberta."
  },
  {
    "timestamp": "2025-06-17T14:03:52.495067+00:00",
    "topico": "alarme/evento",
    "valor": "\ud83d\udea8 Alarme disparado! Porta RECICLO foi aberta."
  },
  {
    "timestamp": "2025-06-17T14:03:52.967710+00:00",
    "topico": "alarme/evento",
    "valor": "\ud83d\udea8 Alarme disparado! Porta RECICLO foi aberta."
  },
  {
    "timestamp": "2025-06-17T14:03:53.532604+00:00",
    "topico": "alarme/evento",
    "valor": "\ud83d\udea8 Alarme disparado! Porta RECICLO foi aberta."
  },
  {
    "timestamp": "2025-06-17T14:03:54.069233+00:00",
    "topico": "alarme/evento",
    "valor": "\ud83d\udea8 Alarme disparado! Porta RECICLO foi aberta."
  },
  {
    "timestamp": "2025-06-17T14:03:54.581859+00:00",
    "topico": "alarme/evento",
    "valor": "\ud83d\udea8 Alarme disparado! Porta RECICLO foi aberta."
  },
  {
    "timestamp": "2025-06-17T14:03:55.109240+00:00",
    "topico": "alarme/evento",
    "valor": "\ud83d\udea8 Alarme disparado! Porta TRIAGEM foi aberta."
  },
  {
    "timestamp": "2025-06-17T14:03:55.619664+00:00",
    "topico": "alarme/evento",
    "valor": "\ud83d\udea8 Alarme disparado! Porta TRIAGEM foi aberta."
  },
  {
    "timestamp": "2025-06-17T14:03:56.121835+00:00",
    "topico": "alarme/evento",
    "valor": "\ud83d\udea8 Alarme disparado! Porta TRIAGEM foi aberta."
  },
  {
    "timestamp": "2025-06-17T14:03:56.640197+00:00",
    "topico": "alarme/evento",
    "valor": "\ud83d\udea8 Alarme disparado! Porta TRIAGEM foi aberta."
  },
  {
    "timestamp": "2025-06-17T14:03:57.171226+00:00",
    "topico": "alarme/evento",
    "valor": "\ud83d\udea8 Alarme disparado! Porta TRIAGEM foi aberta."
  },
  {
    "timestamp": "2025-06-17T14:03:57.712945+00:00",
    "topico": "alarme/evento",
    "valor": "\ud83d\udea8 Alarme disparado! Porta TRIAGEM foi aberta."
  },
  {
    "timestamp": "2025-06-17T14:03:58.222074+00:00",
    "topico": "alarme/evento",
    "valor": "\ud83d\udea8 Alarme disparado! Porta TRIAGEM foi aberta."
  },
  {
    "timestamp": "2025-06-17T14:03:58.775080+00:00",
    "topico": "alarme/evento",
    "valor": "\ud83d\udea8 Alarme disparado! Porta TRIAGEM foi aberta."
  },
  {
    "timestamp": "2025-06-17T14:03:59.262690+00:00",
    "topico": "alarme/evento",
    "valor": "\ud83d\udea8 Alarme disparado! Porta TRIAGEM foi aberta."
  },
  {
    "timestamp": "2025-06-17T14:03:59.850427+00:00",
    "topico": "alarme/evento",
    "valor": "\ud83d\udea8 Alarme disparado! Porta TRIAGEM foi aberta."
  },
  {
    "timestamp": "2025-06-17T14:04:00.382544+00:00",
    "topico": "alarme/evento",
    "valor": "\ud83d\udea8 Alarme disparado! Porta TRIAGEM foi aberta."
  },
  {
    "timestamp": "2025-06-17T14:04:00.888676+00:00",
    "topico": "alarme/evento",
    "valor": "\ud83d\udea8 Alarme disparado! Porta TRIAGEM foi aberta."
  },
  {
    "timestamp": "2025-06-17T14:04:01.521449+00:00",
    "topico": "alarme/evento",
    "valor": "\ud83d\udea8 Alarme disparado! Porta BAZAR foi aberta."
  },
  {
    "timestamp": "2025-06-17T14:04:02.031477+00:00",
    "topico": "alarme/evento",
    "valor": "\ud83d\udea8 Alarme disparado! Porta BAZAR foi aberta."
  },
  {
    "timestamp": "2025-06-17T14:04:02.600754+00:00",
    "topico": "alarme/evento",
    "valor": "\ud83d\udea8 Alarme disparado! Porta BAZAR foi aberta."
  },
  {
    "timestamp": "2025-06-17T14:04:03.114912+00:00",
    "topico": "alarme/evento",
    "valor": "\ud83d\udea8 Alarme disparado! Porta BAZAR foi aberta."
  },
  {
    "timestamp": "2025-06-17T14:04:03.671635+00:00",
    "topico": "alarme/evento",
    "valor": "\ud83d\udea8 Alarme disparado! Porta BAZAR foi aberta."
  },
  {
    "timestamp": "2025-06-17T14:04:04.158251+00:00",
    "topico": "alarme/evento",
    "valor": "\ud83d\udea8 Alarme disparado! Porta BAZAR foi aberta."
  },
  {
    "timestamp": "2025-06-17T14:04:04.686654+00:00",
    "topico": "alarme/evento",
    "valor": "\ud83d\udea8 Alarme disparado! Porta BAZAR foi aberta."
  },
  {
    "timestamp": "2025-06-17T14:04:05.165264+00:00",
    "topico": "alarme/evento",
    "valor": "\ud83d\udea8 Alarme disparado! Porta BAZAR foi aberta."
  },
  {
    "timestamp": "2025-06-17T14:04:05.655555+00:00",
    "topico": "alarme/evento",
    "valor": "\ud83d\udea8 Alarme disparado! Porta BAZAR foi aberta."
  },
  {
    "timestamp": "2025-06-17T14:04:06.208456+00:00",
    "topico": "alarme/evento",
    "valor": "\ud83d\udea8 Alarme disparado! Porta BAZAR foi aberta."
  },
  {
    "timestamp": "2025-06-17T14:04:06.763077+00:00",
    "topico": "alarme/evento",
    "valor": "\ud83d\udea8 Alarme disparado! Porta BAZAR foi aberta."
  },
  {
    "timestamp": "2025-06-17T14:04:07.308667+00:00",
    "topico": "alarme/evento",
    "valor": "\ud83d\udea8 Alarme disparado! Porta BAZAR foi aberta."
  },
  {
    "timestamp": "2025-06-17T14:04:07.860353+00:00",
    "topico": "alarme/evento",
    "valor": "\ud83d\udea8 Alarme disparado! Porta BAZAR foi aberta."
  },
  {
    "timestamp": "2025-06-17T14:04:08.403840+00:00",
    "topico": "alarme/evento",
    "valor": "\ud83d\udea8 Alarme disparado! Porta BAZAR foi aberta."
  },
  {
    "timestamp": "2025-06-17T14:04:08.874356+00:00",
    "topico": "alarme/evento",
    "valor": "\ud83d\udea8 Alarme disparado! Porta BAZAR foi aberta."
  },
  {
    "timestamp": "2025-06-17T14:04:09.490967+00:00",
    "topico": "alarme/evento",
    "valor": "\ud83d\udea8 Alarme disparado! Porta BAZAR foi aberta."
  },
  {
    "timestamp": "2025-06-17T14:04:09.948513+00:00",
    "topico": "alarme/evento",
    "valor": "\ud83d\udea8 Alarme disparado! Porta BAZAR foi aberta."
  },
  {
    "timestamp": "2025-06-17T14:04:10.481236+00:00",
    "topico": "alarme/evento",
    "valor": "\ud83d\udea8 Alarme disparado! Porta BAZAR foi aberta."
  },
  {
    "timestamp": "2025-06-17T14:04:11.019634+00:00",
    "topico": "alarme/evento",
    "valor": "\ud83d\udea8 Alarme disparado! Porta BAZAR foi aberta."
  },
  {
    "timestamp": "2025-06-17T14:04:11.524810+00:00",
    "topico": "alarme/evento",
    "valor": "\ud83d\udea8 Alarme disparado! Porta BAZAR foi aberta."
  },
  {
    "timestamp": "2025-06-17T14:04:12.085636+00:00",
    "topico": "alarme/evento",
    "valor": "\ud83d\udea8 Alarme disparado! Porta BAZAR foi aberta."
  },
  {
    "timestamp": "2025-06-17T14:04:12.597459+00:00",
    "topico": "alarme/evento",
    "valor": "\ud83d\udea8 Alarme disparado! Porta BAZAR foi aberta."
  },
  {
    "timestamp": "2025-06-17T14:04:13.178392+00:00",
    "topico": "alarme/evento",
    "valor": "\ud83d\udea8 Alarme disparado! Porta TRIAGEM foi aberta."
  },
  {
    "timestamp": "2025-06-17T14:04:13.706105+00:00",
    "topico": "alarme/evento",
    "valor": "\ud83d\udea8 Alarme disparado! Porta TRIAGEM foi aberta."
  },
  {
    "timestamp": "2025-06-17T14:04:14.231466+00:00",
    "topico": "alarme/evento",
    "valor": "\ud83d\udea8 Alarme disparado! Porta TRIAGEM foi aberta."
  },
  {
    "timestamp": "2025-06-17T14:04:14.714489+00:00",
    "topico": "alarme/evento",
    "valor": "\ud83d\udea8 Alarme disparado! Porta TRIAGEM foi aberta."
  },
  {
    "timestamp": "2025-06-17T14:04:15.295108+00:00",
    "topico": "alarme/evento",
    "valor": "\ud83d\udea8 Alarme disparado! Porta TRIAGEM foi aberta."
  },
  {
    "timestamp": "2025-06-17T14:04:15.798741+00:00",
    "topico": "alarme/evento",
    "valor": "\ud83d\udea8 Alarme disparado! Porta TRIAGEM foi aberta."
  },
  {
    "timestamp": "2025-06-17T14:04:16.347648+00:00",
    "topico": "alarme/evento",
    "valor": "\ud83d\udea8 Alarme disparado! Porta TRIAGEM foi aberta."
  },
  {
    "timestamp": "2025-06-17T14:04:16.947176+00:00",
    "topico": "alarme/evento",
    "valor": "\ud83d\udea8 Alarme disparado! Porta TRIAGEM foi aberta."
  },
  {
    "timestamp": "2025-06-17T14:04:17.457805+00:00",
    "topico": "alarme/evento",
    "valor": "\ud83d\udea8 Alarme disparado! Porta TRIAGEM foi aberta."
  },
  {
    "timestamp": "2025-06-17T14:04:17.916497+00:00",
    "topico": "alarme/evento",
    "valor": "\ud83d\udea8 Alarme disparado! Porta RECICLO foi aberta."
  },
  {
    "timestamp": "2025-06-17T14:04:18.749041+00:00",
    "topico": "alarme/evento",
    "valor": "\ud83d\udea8 Alarme disparado! Porta RECICLO foi aberta."
  },
  {
    "timestamp": "2025-06-17T14:04:19.162890+00:00",
    "topico": "alarme/evento",
    "valor": "\ud83d\udea8 Alarme disparado! Porta RECICLO foi aberta."
  },
  {
    "timestamp": "2025-06-17T14:04:19.669319+00:00",
    "topico": "alarme/evento",
    "valor": "\ud83d\udea8 Alarme disparado! Porta RECICLO foi aberta."
  },
  {
    "timestamp": "2025-06-17T14:04:20.106671+00:00",
    "topico": "alarme/evento",
    "valor": "\ud83d\udea8 Alarme disparado! Porta RECICLO foi aberta."
  },
  {
    "timestamp": "2025-06-17T14:04:20.690444+00:00",
    "topico": "alarme/evento",
    "valor": "\ud83d\udea8 Alarme disparado! Porta RECICLO foi aberta."
  },
  {
    "timestamp": "2025-06-17T14:04:21.206997+00:00",
    "topico": "alarme/evento",
    "valor": "\ud83d\udea8 Alarme disparado! Porta RECICLO foi aberta."
  },
  {
    "timestamp": "2025-06-17T14:04:21.676685+00:00",
    "topico": "alarme/evento",
    "valor": "\ud83d\udea8 Alarme disparado! Porta RECICLO foi aberta."
  },
  {
    "timestamp": "2025-06-17T14:04:22.244543+00:00",
    "topico": "alarme/evento",
    "valor": "\ud83d\udea8 Alarme disparado! Porta RECICLO foi aberta."
  },
  {
    "timestamp": "2025-06-17T14:04:22.756091+00:00",
    "topico": "alarme/evento",
    "valor": "\ud83d\udea8 Alarme disparado! Porta TRIAGEM foi aberta."
  },
  {
    "timestamp": "2025-06-17T14:04:23.246070+00:00",
    "topico": "alarme/evento",
    "valor": "\ud83d\udea8 Alarme disparado! Porta TRIAGEM foi aberta."
  },
  {
    "timestamp": "2025-06-17T14:04:23.888456+00:00",
    "topico": "alarme/evento",
    "valor": "\ud83d\udea8 Alarme disparado! Porta TRIAGEM foi aberta."
  },
  {
    "timestamp": "2025-06-17T14:04:24.452820+00:00",
    "topico": "alarme/evento",
    "valor": "\ud83d\udea8 Alarme disparado! Porta BAZAR foi aberta."
  },
  {
    "timestamp": "2025-06-17T14:04:24.961988+00:00",
    "topico": "alarme/evento",
    "valor": "\ud83d\udea8 Alarme disparado! Porta BAZAR foi aberta."
  },
  {
    "timestamp": "2025-06-17T14:04:25.491133+00:00",
    "topico": "alarme/evento",
    "valor": "\ud83d\udea8 Alarme disparado! Porta BAZAR foi aberta."
  }
]